<?xml version="1.0" encoding="UTF-8"?>
<?xml-stylesheet type="text/xsl" href="book.xsl" ?>
<b:book xmlns:b="http://cocoaneheads.github.io/iPhone/book.xsd" xmlns="http://www.w3.org/1999/xhtml"
              issue="2" year="2012">
  <b:title>App programmieren für iPhone und iPad</b:title>
  <b:branch>Auflage_2</b:branch>
  <b:errors>
    <b:error pages="81">
      <b:text>Der erste Klammeraffe in Listing 2.8 muss durch <tt>nil</tt> ersetzt werden:
        <pre>
- (void)viewDidLoad {
    [super viewDidLoad];
    [self.textView setText:<b>nil</b>];
    [self writeLog:@"viewDidLoad"];
}</pre>
      </b:text>
      <b:credits>Matthias</b:credits>
    </b:error>
    <b:error pages="82">
      <b:text>Der Parameter der Methode <tt>writeLog:</tt> muss <tt>inLogString</tt> heißen:
        <pre>- (void)writeLog:(NSString *)<b>inLogString</b> {</pre>
      </b:text>
      <b:credits>Timmy</b:credits>
    </b:error>
    <b:error pages="87">
      <b:text>In der Klassendeklaration von <tt>Model</tt> fehlt der Bezeichner für das erste Attribut:
        <pre>
@interface Model : NSObject {
@private
    NSString *<b>status</b>;
    NSDate *creation;
    NSString *name;
    NSMutableArray *objects;
}
@end</pre>
      </b:text>
      <b:credits>Werner</b:credits>
    </b:error>
    <b:error pages="89, 91 und 116">
      <b:text>Bei den <tt>@synthesize</tt>-Anweisungen fehlt der Bezeichner:
<pre>
@synthesize <b>status</b>;
@synthesize name;
@synthesize creation;
</pre></b:text>
      <b:credits>Claus, Timmy und Fabian</b:credits>
    </b:error>
    <b:error pages="90">
      <b:text>In der ersten Anweisung im grauen Kasten fehlt eine schließende Klammer:
<pre>[[self user] setName:[textField text]<b>]</b>;</pre></b:text>
      <b:credits>Matz</b:credits>
    </b:error>
    <b:error pages="103">
      <b:text>Die Methode in der Klasse <tt>Model</tt> heißt <tt>updateDroids:</tt> nicht <tt>updateModel:</tt>.<br /></b:text>
      <b:credits>Hr. Maier</b:credits>
    </b:error>
    <b:error pages="105">
      <b:text>Im ersten Satz des letzt Absatzes steht die falsche Klasse (<tt>Model</tt>). Richtig ist stattdessen <tt>Droid</tt>.<br /></b:text>
      <b:credits>Timmy</b:credits>
    </b:error>
    <b:error pages="121">
      <b:text>In Listing 2.56 hat sich ein überflüssiges <tt>#zonk</tt> eingeschlichen.<br/></b:text>
      <b:credits>Claus</b:credits>
    </b:error>
    <b:error pages="121">
      <b:text>In den Listing 2.55 bis 2.57 und 2.59 fehlen die Namen der Schlüssel; es muss dort jeweils <tt>@"status"</tt> anstatt <tt>@""</tt> heißen.</b:text>
    </b:error>
    <b:error pages="123f">
      <b:text>Der Schlüssel in Listing 2.63 muss <tt>countOfObjects</tt> und nicht <tt>objects</tt> lauten.<br /></b:text>
      <b:credits>Fabian</b:credits>
    </b:error>
    <b:error pages="183">
      <b:text>Listing 2.116 verwendet das falsche Format für <tt>float</tt>:
<pre>
NSNumber *theValue = [NSNumber numberWithInt:42];
NSLog(@"int = %d", [theValue intValue]);
NSLog(@"float = <b>%f</b>", [theValue floatValue]);
NSLog(@"BOOL = %@«, [theValue boolValue] ? @"YES" : @"NO"]
</pre></b:text>
      <b:credits>Sven</b:credits>
    </b:error>
    <b:error pages="187">
      <b:text>Der Schlüssel muss <em>city</em> heißen:
<pre>
[theDictionary valueForKey:@"city"] // Fehler
[theDictionary objectForKey:@"<b>city</b>"] // OK -> nil
</pre></b:text>
      <b:credits>Sven</b:credits>
    </b:error>
    <b:error pages="219">
      <b:text>Die Oder-Operatoren "|" sind in Listing 3.10 beim Satz verlorengegangen. Der Anfang der Methode muss lauten:
<pre>
CGContextRef theContext = UIGraphicsGetCurrentContext();
CGPoint theCenter = [self midPoint];
CGFloat theRadius = CGRectGetWidth(self.bounds) / 2.0;
NSDateComponents *theComponents =
    [self.calendar components:<b>NSHourCalendarUnit |
                          NSMinuteCalendarUnit |
                          NSSecondCalendarUnit</b>
                     fromDate:self.time];
</pre></b:text>
      <b:credits>Thomas</b:credits>
    </b:error>
    <b:error pages="238">
      <b:text>In Listing 3.23 fehlt ein <tt>self</tt>:
<pre>
- (void)viewDidAppear:(BOOL)inAnimated {
    [super viewDidAppear:inAnimated];
    [<b>self</b>.clockView startAnimation];
}
</pre></b:text>
      <b:credits>Thomas</b:credits>
    </b:error>
    <b:error pages="249">
      <b:text>Die Erzeugung der Dateien <em>UIView+AlarmClock.h</em> und <em>UIView+AlarmClock.m</em>
        erfolgt über die Vorlage <em>Objective-C category</em> anstelle von
        <em>Objective-C class extension</em>.<br /></b:text>
      <b:credits>Thomas</b:credits>
    </b:error>
    <b:error pages="259">
      <b:text>Hier fehlt für neuere Xcode-Versionen ein Hinweis, welcher Übergangstyp im schwarzen Popup-Fenster
        (am besten <em>modal</em>) auszuwählen ist.<br /></b:text>
      <b:credits>Sven</b:credits>
    </b:error>
    <b:error pages="271">
      <b:text><pre>NSTimeInterval theTime = self.startTimeOfCurrentDay + <b>self.</b>clockControl.time;</pre></b:text>
      <b:credits>Sven</b:credits>
    </b:error>
    <b:error pages="387">
      <b:text>Die seltsamen Zeichen am Ende einiger Zeilen von Listing 4.50 stehen für Zeilenumbrüche und können ignoriert werden.</b:text>
    </b:error>
    <b:error pages="781">
      <b:text>Listing 8.8 verwendet nicht die Variable <tt>theEncoding</tt> für die Konverterung:
<pre>
- (NSString *)encodedStringForURLWithEncoding:
    (NSStringEncoding)inEncoding {
    CFStringEncoding theEncoding =
        CFStringConvertNSStringEncodingToEncoding(
            inEncoding);
    CFStringRef theResult =
        CFURLCreateStringByAddingPercentEscapes(
            kCFAllocatorDefault,
            (__bridge CFStringRef)self,
            NULL,
            (CFStringRef)@"!*'();:@&amp;=+$,/?%#[]",
            <b>theEncoding</b>);

    return (__bridge_transfer NSString *)theResult;
}
</pre></b:text>
      <b:credits>Claus</b:credits>
    </b:error>
    <b:error pages="832">
      <b:text>In Listing 8.48 fehlt ein <em>e</em> im Variablennamen:
<pre>if(theError == nil &amp;&amp;
    [theR<b>e</b>sponse isKindOfClass:[NSHTTPURLResponse class]] &amp;&amp;
    [theResponse statusCode] == 200) {</pre>
      </b:text>
      <b:credits>Matz</b:credits>
    </b:error>
    <b:error pages="852">
      <b:text>In Listing 8.63 hat sich ein überflüssiges <tt>#zonk#</tt> eingeschlichen.</b:text>
    </b:error>
  </b:errors>
</b:book>